{
    "keep": {
        "days": true,
        "amount": 14
    },
    "auditLog": "C:\\Users\\hoang\\OneDrive\\Documents\\TERM 8\\THESIS PROJECT\\Ecommerce\\thesis-ecommerce-system\\src\\api\\v1\\logs\\.e5cd46d3774fe5b49ceeac61974ff3e4d461078a-audit.json",
    "files": [
        {
            "date": 1771834553593,
            "name": "C:\\Users\\hoang\\OneDrive\\Documents\\TERM 8\\THESIS PROJECT\\Ecommerce\\thesis-ecommerce-system\\src\\api\\v1\\logs\\application-2026-02-23.info.log",
            "hash": "2d7a6247568270814c91ec81c5020672e8b2534290160bddb1e5bd3a42c317e7"
        },
        {
            "date": 1771897954379,
            "name": "C:\\Users\\hoang\\OneDrive\\Documents\\TERM 8\\THESIS PROJECT\\Ecommerce\\thesis-ecommerce-system\\src\\api\\v1\\logs\\application-2026-02-24.info.log",
            "hash": "ac4069678a4ad7a53643876aa906840c30d99fb8556b6f78df7f351c57f709f4"
        },
        {
            "date": 1771991551975,
            "name": "C:\\Users\\hoang\\OneDrive\\Documents\\TERM 8\\THESIS PROJECT\\Ecommerce\\thesis-ecommerce-system\\src\\api\\v1\\logs\\application-2026-02-25.info.log",
            "hash": "43317efca4f985e06d2a498291ce200adabd94367b3b82816ee3e41d90effcc3"
        },
        {
            "date": 1772764449869,
            "name": "C:\\Users\\hoang\\OneDrive\\Documents\\TERM 8\\THESIS PROJECT\\Ecommerce\\thesis-ecommerce-system\\src\\api\\v1\\logs\\application-2026-03-06.info.log",
            "hash": "eabcce4ea1f4de009ec547f20a81dc0435ea1492571feb7b9aeecf878bd79edc"
        }
    ],
    "hashType": "sha256"
}